setup.cfg
setup.py
Test/__init__.py
Test/file1.py
Test/file2.py
Test_01.egg-info/PKG-INFO
Test_01.egg-info/SOURCES.txt
Test_01.egg-info/dependency_links.txt
Test_01.egg-info/requires.txt
Test_01.egg-info/top_level.txt