Metadata-Version: 1.1
Name: Test-01
Version: 0.2
Summary: Speed up your model making process. This will help you in selecting best features, best Models (SVM,SVR Random Fotest e.t.c and also in Data Preprocessing
Home-page: https://github.com/SSudhashu/Test
Author: Sudhanshu Pandey
Author-email: sudhanshu.dpandey@gmail.com
License: MIT
Download-URL: https://github.com/SSudhashu/Test/archive/v0.2.tar.gz
Keywords: Machine Learning,Model,Regression,Classification,Automation,Data Preprocessing,Preprocessing,Feature Selection,Model Selection,SVM
Platform: UNKNOWN
Classifier: Development Status :: 3 - Alpha
Classifier: Topic :: Scientific/Engineering :: Artificial Intelligence
Classifier: Intended Audience :: Education
Classifier: Operating System :: Microsoft :: Windows :: Windows 10
Classifier: License :: OSI Approved :: MIT License
Classifier: Programming Language :: Python :: 3
